tests/__init__.py
tests/disable_test_connectors.py
tests/disable_test_connectors_default_org.py
tests/test_aa_permissions.py
tests/test_api_manager.py
tests/test_api_manager_default_org.py
tests/test_asset_access.py
tests/test_graph_v2.py
tests/test_graph_v2_default_org.py
tests/test_hierarchies.py
tests/test_hierarchies_default_org.py
tests/test_org_admin.py
tests/test_org_admin_default_org.py
tests/test_pipelines.py
tests/test_pipelines_default_org.py
tests/test_properties.py
tests/test_sources.py
tests/test_sources_default_org.py
tests/test_templates.py
tests/test_templates_default_org.py
unify/Unify.py
unify/WaitingLibrary.py
unify/__init__.py
unify/_version.py
unify/apimanager.py
unify/apirequestsmng.py
unify/apiutils.py
unify/assetaccess.py
unify/clusters.py
unify/connectors.py
unify/generalutils.py
unify/graph.py
unify/hierarchies.py
unify/orgadmin.py
unify/permissions.py
unify/pipelines.py
unify/properties.py
unify/sources.py
unify/templates.py
unify/users.py
unify/helpers/SingleOrg.py
unify/helpers/__init__.py
unify/helpers/staticsql.py
unify/helpers/Permissions/__init__.py
unify/helpers/datasets/__init__.py
unify/helpers/datasets/column.py
unify/helpers/graph_ql/__init__.py
unify/helpers/graph_ql/dataset_gql.py
unify/helpers/graph_ql/gql_query_builder.py
unify/helpers/graph_ql/graphql.py
unify/helpers/graph_ql/permissions.py
unify/helpers/graph_ql/pipeline_gql.py
unify/helpers/pipeline/__init__.py
unify/helpers/pipeline/flow_column.py
unify/helpers/pipeline/schema.py
unify/helpers/unify_objects/Template.py
unify/helpers/unify_objects/__init__.py
unify_sdk-4.2.6.dist-info/LICENSE
unify_sdk-4.2.6.dist-info/METADATA
unify_sdk-4.2.6.dist-info/WHEEL
unify_sdk-4.2.6.dist-info/top_level.txt
unify_sdk-4.2.6.dist-info/RECORD
