Metadata-Version: 2.1
Name: unify-sdk
Version: 4.2.6
Summary: Unify Python SDK
Home-page: https://github.com/ElementAnalytics/unify-python-sdk
Author: Element Analytics
Author-email: platform@ean.io
License: UNKNOWN
Platform: UNKNOWN
Classifier: Programming Language :: Python :: 3
Classifier: Programming Language :: Python :: 3.7
Requires-Python: >=3
License-File: LICENSE
Requires-Dist: keyring
Requires-Dist: setuptools
Requires-Dist: tabulate
Requires-Dist: requests
Requires-Dist: json-lines
